HoloTTS/HoloTTS.py
HoloTTS/__init__.py
holotts-0.2.6.dist-info/METADATA
holotts-0.2.6.dist-info/WHEEL
holotts-0.2.6.dist-info/top_level.txt
holotts-0.2.6.dist-info/RECORD
