Metadata-Version: 2.4
Name: HoloTTS
Version: 0.2.6
Summary: Modern, local TTS, advanced audio manipulation, pipeline automation, and flexible playback, pause, resume for modern AI-driven applications
Author: Tristan McBride Sr.
Author-email: "Tristan McBride Sr." <142635792+TristanMcBrideSr@users.noreply.github.com>
Maintainer-email: "Tristan McBride Sr." <142635792+TristanMcBrideSr@users.noreply.github.com>
License-Expression: Apache-2.0
Project-URL: Homepage, https://github.com/TristanMcBrideSr
Keywords: AI,Agents,Speech Synthesis,Productivity,Automation
Classifier: Programming Language :: Python :: 3
Classifier: Operating System :: OS Independent
Classifier: Intended Audience :: Developers
Requires-Python: >=3.10
Requires-Dist: pyttsx3
Requires-Dist: pyttsx4
Requires-Dist: python-dotenv
Requires-Dist: pydub
Requires-Dist: numpy
Requires-Dist: kokoro
Requires-Dist: SoundFile
Requires-Dist: pygame
Requires-Dist: pyautogui
Dynamic: author
